pundle.py
pundle-0.9.2.dist-info/LICENSE.txt
pundle-0.9.2.dist-info/METADATA
pundle-0.9.2.dist-info/WHEEL
pundle-0.9.2.dist-info/entry_points.txt
pundle-0.9.2.dist-info/top_level.txt
pundle-0.9.2.dist-info/RECORD
