Metadata-Version: 2.1
Name: pundle
Version: 0.9.2
Summary: Requirements management tool.
Home-page: https://github.com/Deepwalker/pundler/
Author: Deepwalker
Author-email: krivushinme@gmail.com
License: BSD
Keywords: bundler virtualenv pip install package setuptools
Platform: UNKNOWN
Classifier: Intended Audience :: Developers
Classifier: License :: OSI Approved :: BSD License
Classifier: Operating System :: OS Independent
Classifier: Programming Language :: Python
Classifier: Programming Language :: Python :: 3
